biomeai/__init__.py
biomeai/colabfold.py
biomeai/core.py
biomeai-1.0.0.dist-info/licenses/LICENSE
biomeai-1.0.0.dist-info/METADATA
biomeai-1.0.0.dist-info/WHEEL
biomeai-1.0.0.dist-info/top_level.txt
biomeai-1.0.0.dist-info/RECORD
